{
  "title": "Experience",
  "companies": [
    {
      "name": "PacketFront Software",
      "code": "packet",
      "summary": "As the sole frontend developer on my team, I'm responsible for the development of the graphical user interface (GUI) for a network orchestration system",
      "stack": ["JavaScript", "jQuery", "Vert.x", "Java", "Robot Framework", "JSON-RPC", "SOAP"],
      "roles": [
        {
          "name": "Frontend developer",
          "date": "Jul 2023 - current",
          "responsibilities" : [
            "Implement new features and resolve bugs using JavaScript, jQuery, and Java (Vert.x) for both front-end and back-end",
            "Create and maintain dynamic web page templates using FreeMarker Template Language (FTL)",
            "Refactor and optimize legacy code to improve performance, maintainability, and user experience",
            "Develop and integrate API methods using JSON-RPC to enable communication between the front-end and core module",
            "Create and maintain automated end-to-end (e2e) tests in the Robot Framework to ensure reliable and high-quality GUI functionality",
            "Drive the modernization of the system’s appearance, enhancing visual appeal and usability"
          ]
        }
      ]
    },
    {
      "name": "EPAM Systems",
      "code": "epam",
      "summary": "",
      "stack": [],
      "roles": [
        {
          "name": "Frontend developer",
          "date": "Jan 2022 - Jun 2023",
          "responsibilities" : [
            "Creating e-commerces in Angular 11 and SAP Spartacus",
            "Developing new features",
            "Creating reusable components",
            "Modifying existing classes",
            "Implementing application state in NgRx",
            "Maintaining and developing internal libraries",
            "Integrating external payment methods",
            "Configuring Google Analytics Events" ,
            "Working in SCRUM methodology"
            
          ]
        }
      ]
    },
    {
      "name": "Centralny Ośrodek Informatyki",
      "code": "coi",
      "summary": "",
      "stack": [],
      "roles": [
        {
          "name": "Frontend developer",
          "date": "Feb 2021 - Dec 2021",
          "responsibilities" : [
            "Adding new features to existing code in JavaScript",
            "Adding new features to existing services (Angular)",
            "Taking part in the development, design, and analysis of the system for officials"
          ]
        },
        {
          "name": "Junior Frontend developer",
          "date": "Apr 2020 - Jan 2021",
          "responsibilities" : [
            "Developing new online services for citizens",
            "Fixing bugs in existing services",
            "Updating, maintaining, and creating new components",
            "Cooperating with UX/UI designers, analysts, and backen developers"
          ]
        },
        {
          "name": "Intern",
          "date": "Jan 2020 - Mar 2020",
          "responsibilities" : [
            "Fixing bugs in existing services",
            "Familiarizing yourself with the projects"
          ]
        }
      ]
    },
    {
      "name": "Academic Partners Foundation",
      "code": "apf",
      "summary": "",
      "stack": [],
      "roles": [
        {
          "name": "Junior UX/UI Designer",
          "date": "Jul 2018 - Jan 2019",
          "responsibilities" : [
            "Prototyping and designing websites",
            "Editing HTML and CSS files",
            "Writing specifications for developers",
            "Manual testing websites",
            "Copywriting"
          ]
        }
      ]
    }
  ]
}